package/__init__.py
package/topsis.py
topsis_Aarushi_102003527-1.1.1.dist-info/LICENSE
topsis_Aarushi_102003527-1.1.1.dist-info/METADATA
topsis_Aarushi_102003527-1.1.1.dist-info/WHEEL
topsis_Aarushi_102003527-1.1.1.dist-info/top_level.txt
topsis_Aarushi_102003527-1.1.1.dist-info/RECORD
