Metadata-Version: 2.1
Name: topsis-Aarushi-102003527
Version: 1.1.1
Summary: It evaluates alternatives based on multiple criteria using TOPSIS method
Home-page: https://github.com/aarushi353/Topsis
Author: Aarushi Abrol
Author-email: <aabrol_be20@thapar.edu>
Classifier: Programming Language :: Python :: 3
Classifier: Operating System :: Unix
Classifier: Operating System :: MacOS :: MacOS X
Classifier: Operating System :: Microsoft :: Windows
License-File: LICENSE
